LICENSE
README.md
setup.py
yggzslib/__init__.py
yggzslib.egg-info/PKG-INFO
yggzslib.egg-info/SOURCES.txt
yggzslib.egg-info/dependency_links.txt
yggzslib.egg-info/top_level.txt
yggzslib/encode/__init__.py