Metadata-Version: 2.1
Name: yggzslib
Version: 0.0.13
Summary: 阳光工作室
Home-page: https://github.com/
Author: Haoyang Zhang
Author-email: 1@yangguang-gongzuoshi.top
Classifier: Programming Language :: Python :: 3
Classifier: License :: OSI Approved :: MIT License
Classifier: Operating System :: OS Independent
License-File: LICENSE
